fastapi_example_server/.DS_Store
fastapi_example_server/.pytest_cache/.gitignore
fastapi_example_server/.pytest_cache/CACHEDIR.TAG
fastapi_example_server/.pytest_cache/README.md
fastapi_example_server/.pytest_cache/v/cache/nodeids
fastapi_example_server/.pytest_cache/v/cache/stepwise
fastapi_example_server/__init__.py
fastapi_example_server/app.py
fastapi_example_server/doc.py
fastapi_example_server/dummy_data.py
fastapi_example_server/exceptions.py
fastapi_example_server/main.py
fastapi_example_server/models/__init__.py
fastapi_example_server/models/items.py
fastapi_example_server-0.1.1.dist-info/entry_points.txt
fastapi_example_server-0.1.1.dist-info/WHEEL
fastapi_example_server-0.1.1.dist-info/METADATA
fastapi_example_server-0.1.1.dist-info/RECORD
